webint_player/__init__.py
webint_player/templates/__init__.py
webint_player/templates/index.html
webint_player-0.0.3.dist-info/METADATA
webint_player-0.0.3.dist-info/entry_points.txt
webint_player-0.0.3.dist-info/WHEEL
webint_player-0.0.3.dist-info/RECORD
